wica/__init__.py
wica/examples.py
wica/exceptions.py
wica/sseclient.py
wica/utils.py
wica/wica.py
asyncpywica-1.0.1.dist-info/LICENSE
asyncpywica-1.0.1.dist-info/WHEEL
asyncpywica-1.0.1.dist-info/METADATA
asyncpywica-1.0.1.dist-info/RECORD
