Metadata-Version: 2.1
Name: asyncpywica
Version: 1.0.1
Summary: A simple async python API to access wica-http SSE.
Author: Niklas Laufkoetter
Author-email: niklas.laufkoetter@psi.ch
Requires-Python: >=3.8,<4.0
Classifier: Programming Language :: Python :: 3
Classifier: Programming Language :: Python :: 3.8
Classifier: Programming Language :: Python :: 3.9
Classifier: Programming Language :: Python :: 3.10
Classifier: Programming Language :: Python :: 3.11
Requires-Dist: httpx (>=0.23.0,<0.24.0)
Requires-Dist: requests (>=2.28.1,<3.0.0)
